jareds_super_ai/__init__.py
jareds_super_ai/super_ai.py
jareds_super_ai-0.1.0.dist-info/METADATA
jareds_super_ai-0.1.0.dist-info/WHEEL
jareds_super_ai-0.1.0.dist-info/entry_points.txt
jareds_super_ai-0.1.0.dist-info/RECORD
